epe_maria/__init__.py
epe_maria/benchmark.py
epe_maria/core.py
epe_maria/info.py
epe_maria/metrics.py
epe_maria/monitor.py
epe_maria/setup.py
epe_maria/temporal.py
epe_maria/test_temporal.py
epe_maria/utils.py
epe_maria/visuals.py
digamma_prime-0.2.0.dist-info/METADATA
digamma_prime-0.2.0.dist-info/WHEEL
digamma_prime-0.2.0.dist-info/top_level.txt
digamma_prime-0.2.0.dist-info/RECORD
