Metadata-Version: 2.4
Name: digamma_prime
Version: 0.2.0
Summary: Symbolic audit engine for divergence detection and structural analysis
Home-page: https://github.com/Cerene-Salt/Digamma-Prime-Framework
Author: Cerene Salt
Author-email: letskikyou@email.com
License: MIT
Classifier: Programming Language :: Python :: 3.11
Classifier: License :: OSI Approved :: MIT License
Classifier: Operating System :: OS Independent
Requires-Python: >=3.11
Requires-Dist: sympy
Requires-Dist: numpy
Requires-Dist: matplotlib
Dynamic: author
Dynamic: author-email
Dynamic: classifier
Dynamic: description
Dynamic: description-content-type
Dynamic: home-page
Dynamic: license
Dynamic: requires-dist
Dynamic: requires-python
Dynamic: summary
